scoretest/__init__.py
scoretest/core.py
scoretest/diagnostics.py
scoretest/simulation.py
scoretest/utils.py
scoretest/weight_functions.py
tsai_scoretest-1.0.0.dist-info/licenses/LICENSE
tsai_scoretest-1.0.0.dist-info/METADATA
tsai_scoretest-1.0.0.dist-info/WHEEL
tsai_scoretest-1.0.0.dist-info/top_level.txt
tsai_scoretest-1.0.0.dist-info/RECORD
